cross_crypto_py/__init__.py
cross_crypto_py/__init__.pyi
cross_crypto_py/core.py
cross_crypto_py/core.pyi
cross_crypto_py/decrypt.py
cross_crypto_py/decrypt.pyi
cross_crypto_py/encrypt.py
cross_crypto_py/encrypt.pyi
cross_crypto_py/file_crypto.py
cross_crypto_py/file_crypto.pyi
cross_crypto_py/keygen.py
cross_crypto_py/keygen.pyi
cross_crypto_py-1.2.0.dist-info/licenses/LICENSE
cross_crypto_py-1.2.0.dist-info/METADATA
cross_crypto_py-1.2.0.dist-info/WHEEL
cross_crypto_py-1.2.0.dist-info/top_level.txt
cross_crypto_py-1.2.0.dist-info/RECORD
