Metadata-Version: 2.4
Name: cross-crypto-py
Version: 1.2.0
Summary: Cifrado híbrido seguro con interoperabilidad entre lenguajes como Python, TypeScript y Rust, basado en AES-GCM (256 bits) y RSA-OAEP (4096 bits)
Home-page: https://github.com/acadyne/cross-crypto-py
Author: Jose Fabian Soltero Escobar
Author-email: acadyne@gmail.com
License: MIT
Project-URL: Documentation, https://github.com/acadyne/cross-crypto-py#readme
Project-URL: Source, https://github.com/acadyne/cross-crypto-py
Project-URL: Tracker, https://github.com/acadyne/cross-crypto-py/issues
Keywords: encryption,cryptography,security,typescript,python,rsa,aes,hybrid-encryption,cross-platform,secure-communication,data-protection,crypto,gcm,oaep
Classifier: Development Status :: 5 - Production/Stable
Classifier: Intended Audience :: Developers
Classifier: Intended Audience :: System Administrators
Classifier: Topic :: Security
Classifier: Topic :: Security :: Cryptography
Classifier: Topic :: Software Development :: Libraries :: Python Modules
Classifier: License :: OSI Approved :: MIT License
Classifier: Programming Language :: Python :: 3
Classifier: Programming Language :: Python :: 3.7
Classifier: Programming Language :: Python :: 3.8
Classifier: Programming Language :: Python :: 3.9
Classifier: Programming Language :: Python :: 3.10
Classifier: Programming Language :: Python :: 3.11
Classifier: Programming Language :: Python :: 3.12
Classifier: Programming Language :: Python :: Implementation :: CPython
Classifier: Programming Language :: JavaScript
Classifier: Framework :: AsyncIO
Classifier: Operating System :: OS Independent
Classifier: Environment :: Web Environment
Classifier: Natural Language :: English
Classifier: Typing :: Typed
Requires-Python: >=3.7
License-File: LICENSE
Requires-Dist: cryptography>=40.0.2
Requires-Dist: pycryptodome>=3.17
Requires-Dist: dill>=0.3.6
Dynamic: author
Dynamic: author-email
Dynamic: classifier
Dynamic: description
Dynamic: description-content-type
Dynamic: home-page
Dynamic: keywords
Dynamic: license
Dynamic: license-file
Dynamic: project-url
Dynamic: requires-dist
Dynamic: requires-python
Dynamic: summary
